{
  "gem": "{{count}} Gem",
  "gem_plural": "{{count}} Gems",

  "rune0": "Minor Water",
  "rune1": "Minor Nature",
  "rune2": "Minor Fire",
  "rune3": "Minor Wind",
  "rune4": "Minor Magic",
  "rune5": "Minor Earth",
  "rune6": "Major Water",
  "rune7": "Major Nature",
  "rune8": "Major Fire",
  "rune9": "Major Wind",
  "rune10": "Major Magic",
  "rune11": "Major Earth",
  "rune12": "Runic Water",
  "rune13": "Runic Nature",
  "rune14": "Runic Fire",
  "rune15": "Runic Wind",
  "rune16": "Runic Magic",
  "rune17": "Runic Earth",
  "rune18": "Arcane Stoic",
  "rune19": "Arcane Swamp",
  "rune20": "Arcane Blood",
  "rune21": "Arcane Blade",
  "rune22": "Arcane Spirit",
  "rune23": "Arcane Shield",
  "rune24": "Arcane Stealth",
  "rune25": "Arcane Beast",
  "rune26": "Arcane Light",
  "rune27": "Arcane Venom",
  "rune28": "Arcane Forest",
  "rune29": "Arcane Rage",
  "rune30": "Arcane Storm",
  "rune31": "Arcane Dark",
  "rune32": "Arcane Lava",
  "rune33": "Arcane Summer",
  "rune34": "Arcane Plains",
  "rune35": "Arcane Mountain",
  "rune36": "Arcane Death",
  "rune37": "Arcane Skull",
  "rune38": "Arcane Deep",
  "rune39": "Celestial"
}
